pyBedGraph/Benchmark.py
pyBedGraph/Chromosome.py
pyBedGraph/Genome.py
pyBedGraph/__init__.py
pyBedGraph-0.3.1.dist-info/LICENSE
pyBedGraph-0.3.1.dist-info/METADATA
pyBedGraph-0.3.1.dist-info/WHEEL
pyBedGraph-0.3.1.dist-info/top_level.txt
pyBedGraph-0.3.1.dist-info/RECORD
