Metadata-Version: 2.1
Name: pyBedGraph
Version: 0.3.1
Summary: An alternative to pyBigWig for bedgraph files
Home-page: https://github.com/c0ver/pyBedGraph
Author: Henry Zhang
Author-email: henrybzhang.99@gmail.com
License: UNKNOWN
Platform: UNKNOWN
Classifier: Programming Language :: Python :: 3
Classifier: License :: OSI Approved :: MIT License
Classifier: Operating System :: OS Independent
